MANIFEST.in
README.rst
setup.cfg
setup.py
tw2/__init__.py
tw2.jqplugins.jqgrid.egg-info/PKG-INFO
tw2.jqplugins.jqgrid.egg-info/SOURCES.txt
tw2.jqplugins.jqgrid.egg-info/dependency_links.txt
tw2.jqplugins.jqgrid.egg-info/entry_points.txt
tw2.jqplugins.jqgrid.egg-info/namespace_packages.txt
tw2.jqplugins.jqgrid.egg-info/not-zip-safe
tw2.jqplugins.jqgrid.egg-info/requires.txt
tw2.jqplugins.jqgrid.egg-info/top_level.txt
tw2/jqplugins/__init__.py
tw2/jqplugins/jqgrid/__init__.py
tw2/jqplugins/jqgrid/base.py
tw2/jqplugins/jqgrid/defaults.py
tw2/jqplugins/jqgrid/samples/__init__.py
tw2/jqplugins/jqgrid/samples/core.py
tw2/jqplugins/jqgrid/samples/model.py
tw2/jqplugins/jqgrid/samples/sqla.py
tw2/jqplugins/jqgrid/static/jquery/plugins/jqGrid/3.6.5/css/ellipsis-xbl.xml
tw2/jqplugins/jqgrid/static/jquery/plugins/jqGrid/3.6.5/css/ui.jqgrid.css
tw2/jqplugins/jqgrid/static/jquery/plugins/jqGrid/3.6.5/js/Changes.txt
tw2/jqplugins/jqgrid/static/jquery/plugins/jqGrid/3.6.5/js/install.txt
tw2/jqplugins/jqgrid/static/jquery/plugins/jqGrid/3.6.5/js/jquery.jqGrid.min.js
tw2/jqplugins/jqgrid/static/jquery/plugins/jqGrid/3.6.5/js/i18n/grid.locale-bg.js
tw2/jqplugins/jqgrid/static/jquery/plugins/jqGrid/3.6.5/js/i18n/grid.locale-bg1251.js
tw2/jqplugins/jqgrid/static/jquery/plugins/jqGrid/3.6.5/js/i18n/grid.locale-cat.js
tw2/jqplugins/jqgrid/static/jquery/plugins/jqGrid/3.6.5/js/i18n/grid.locale-cn.js
tw2/jqplugins/jqgrid/static/jquery/plugins/jqGrid/3.6.5/js/i18n/grid.locale-cs.js
tw2/jqplugins/jqgrid/static/jquery/plugins/jqGrid/3.6.5/js/i18n/grid.locale-de.js
tw2/jqplugins/jqgrid/static/jquery/plugins/jqGrid/3.6.5/js/i18n/grid.locale-dk.js
tw2/jqplugins/jqgrid/static/jquery/plugins/jqGrid/3.6.5/js/i18n/grid.locale-el.js
tw2/jqplugins/jqgrid/static/jquery/plugins/jqGrid/3.6.5/js/i18n/grid.locale-en.js
tw2/jqplugins/jqgrid/static/jquery/plugins/jqGrid/3.6.5/js/i18n/grid.locale-fa.js
tw2/jqplugins/jqgrid/static/jquery/plugins/jqGrid/3.6.5/js/i18n/grid.locale-fi.js
tw2/jqplugins/jqgrid/static/jquery/plugins/jqGrid/3.6.5/js/i18n/grid.locale-fr.js
tw2/jqplugins/jqgrid/static/jquery/plugins/jqGrid/3.6.5/js/i18n/grid.locale-he.js
tw2/jqplugins/jqgrid/static/jquery/plugins/jqGrid/3.6.5/js/i18n/grid.locale-is.js
tw2/jqplugins/jqgrid/static/jquery/plugins/jqGrid/3.6.5/js/i18n/grid.locale-it.js
